urdf_compose/__init__.py
urdf_compose/compose.py
urdf_compose/composed_urdf.py
urdf_compose/connect.py
urdf_compose/py.typed
urdf_compose/resolve_connections.py
urdf_compose/urdf_compose_error.py
urdf_compose/urdf_obj.py
urdf_compose/utils.py
urdf_compose/xml_utils.py
urdf_compose-0.4.1.dist-info/LICENSE
urdf_compose-0.4.1.dist-info/METADATA
urdf_compose-0.4.1.dist-info/WHEEL
urdf_compose-0.4.1.dist-info/entry_points.txt
urdf_compose-0.4.1.dist-info/RECORD
