Metadata-Version: 2.1
Name: urdf-compose
Version: 0.4.1
Summary: Package for dynamically composing URDFs
License: MIT
Author: Zev Minsky-Primus
Author-email: zev@tutorintelligence.com
Requires-Python: >=3.10,<4.0
Classifier: License :: OSI Approved :: MIT License
Classifier: Programming Language :: Python :: 3
Classifier: Programming Language :: Python :: 3.10
Classifier: Programming Language :: Python :: 3.11
Classifier: Programming Language :: Python :: 3.12
